cardano_explorer/__init__.py
cardano_explorer/blockfrost_api.py
cardano_explorer-0.2.0.dist-info/LICENSE.txt
cardano_explorer-0.2.0.dist-info/METADATA
cardano_explorer-0.2.0.dist-info/WHEEL
cardano_explorer-0.2.0.dist-info/top_level.txt
cardano_explorer-0.2.0.dist-info/RECORD
