Metadata-Version: 2.1
Name: cardano-explorer
Version: 0.2.0
Summary: Python wrapper for accessing and processing information stored on the Cardano blockchain using Blockfrost API.
Home-page: https://github.com/djessy-atta/py-cardano-explorer
Author: Djessy ATTA
Author-email: djessyatta@live.fr
License: MIT
Download-URL: https://github.com/djessy-atta/py-cardano-explorer/archive/refs/tags/v0.2-beta.0.tar.gz
Keywords: CARDANO,API,WRAPPER,BLOCKCHAIN,BLOCKFROST
Platform: UNKNOWN
Classifier: Development Status :: 3 - Alpha
Classifier: Intended Audience :: Developers
Classifier: Topic :: Software Development :: Build Tools
Classifier: License :: OSI Approved :: MIT License
Classifier: Programming Language :: Python
Classifier: Programming Language :: Python :: 3
Classifier: Programming Language :: Python :: 3.8
Requires-Dist: pandas (>=1.3.2)
Requires-Dist: requests (>=2.26.0)
Requires-Dist: typing (>=3.7.4.3)
Requires-Dist: numpy (==1.21.2)
Requires-Dist: tqdm (>=4.62.2)
